alexapy/__init__.py
alexapy/alexaapi.py
alexapy/alexahttp2.py
alexapy/alexalogin.py
alexapy/alexaproxy.py
alexapy/alexawebsocket.py
alexapy/const.py
alexapy/errors.py
alexapy/helpers.py
LICENSE
alexapy_test-1.30.9.dist-info/AUTHORS.md
alexapy_test-1.30.9.dist-info/LICENSE
alexapy_test-1.30.9.dist-info/METADATA
alexapy_test-1.30.9.dist-info/WHEEL
alexapy_test-1.30.9.dist-info/RECORD
