Metadata-Version: 2.1
Name: AlexaPy-test
Version: 1.30.9
Summary: Python API to control Amazon Echo Devices Programmatically.
Home-page: https://gitlab.com/figorr1/alexapy
License: Apache-2.0
Keywords: amazon,alexa,homeassistant
Author: figorr
Author-email: jdcuartero@yahoo.es
Requires-Python: >=3.11,<4
Classifier: License :: OSI Approved :: Apache Software License
Classifier: Programming Language :: Python :: 3
Classifier: Programming Language :: Python :: 3.11
Classifier: Programming Language :: Python :: 3.12
Classifier: Programming Language :: Python :: 3.13
Requires-Dist: aiofiles (>=23.1.0,<24.0.0)
Requires-Dist: aiohttp (>=3.8.4,<4.0.0)
Requires-Dist: authcaptureproxy (>=1.3.2,<2.0.0)
Requires-Dist: backoff (>=1.10)
Requires-Dist: beautifulsoup4
Requires-Dist: certifi
Requires-Dist: cryptography (>=35.0)
Requires-Dist: httpx[http2] (>=0.24.0)
Requires-Dist: pyotp (>=2.4)
Requires-Dist: requests
Requires-Dist: simplejson
Requires-Dist: yarl
Project-URL: Repository, https://gitlab.com/figorr1/alexapy
